cycADa/__init__.py
cycada-2025.0.dist-info/METADATA
cycada-2025.0.dist-info/WHEEL
cycada-2025.0.dist-info/top_level.txt
cycada-2025.0.dist-info/RECORD
