Metadata-Version: 2.4
Name: cycADa
Version: 2025.0
Summary: coming soon
